{
  "_baseUrl": "http://portal-homolog.marko.com.br/api/mercury-service",
  "_portalUrl": "http://portal-homolog.marko.com.br/api/portal-service",
  "_tokenUrl": "token",
  "_tokenRefreshUrl": "refresh-token",
  "_authUrl": "identity",
  "_loginUrl": "/sign-in",
  "_identityServiceUrl": "http://portal-homolog.marko.com.br/api/portal-service",
  "_apiSisContatos": "http://portal-homolog.marko.com.br/api/siscontatos-service",
  "_apiRoBim": "http://portal-homolog.marko.com.br/api/robim-service",
  "_appRelease": "1.0.11",
  "_appReleaseDate": "28/08/2023",
  "_appVerssionChech": "http://portal-homolog.marko.com.br/mercury/version.json",

  "baseUrl": "http://portal-dev.marko.com.br/api/mercury-service",
  "portalUrl": "http://portal-dev.marko.com.br/api/portal-service",
  "tokenUrl": "token",
  "tokenRefreshUrl": "refresh-token",
  "authUrl": "identity",
  "loginUrl": "/sign-in",
  "identityServiceUrl": "http://portal-dev.marko.com.br/api/portal-service",
  "apiSisContatos": "http://portal-dev.marko.com.br/api/siscontatos-service",
  "apiRoBim": "http://portal-dev.marko.com.br/api/robim-service",
  "appRelease": "1.02",
  "appReleaseDate": "11/10/2023",
  "appVerssionChech": "http://portal-dev.marko.com.br/mercury/version.json"
}
